{
  "fetchedAt": "2026-07-12T06:42:57.338Z",
  "station": "Tywyn",
  "upcoming": [
    {
      "type": "low",
      "timeIso": "2026-07-12T13:20:00.000Z",
      "timeLabel": "Sun 2:20 pm",
      "heightM": 1.0119623063706251
    },
    {
      "type": "high",
      "timeIso": "2026-07-12T18:34:00.000Z",
      "timeLabel": "Sun 7:34 pm",
      "heightM": 4.411545008176593
    },
    {
      "type": "low",
      "timeIso": "2026-07-13T01:45:00.000Z",
      "timeLabel": "Mon 2:45 am",
      "heightM": 0.7722462280263563
    },
    {
      "type": "high",
      "timeIso": "2026-07-13T07:03:00.000Z",
      "timeLabel": "Mon 8:03 am",
      "heightM": 4.551398416157226
    },
    {
      "type": "low",
      "timeIso": "2026-07-13T14:10:00.000Z",
      "timeLabel": "Mon 3:10 pm",
      "heightM": 0.8238148144275412
    },
    {
      "type": "high",
      "timeIso": "2026-07-13T19:23:00.000Z",
      "timeLabel": "Mon 8:23 pm",
      "heightM": 4.722887756871372
    }
  ]
}
