{
  "fetchedAt": "2026-06-24T16:25:34.142Z",
  "station": "Tywyn",
  "upcoming": [
    {
      "type": "low",
      "timeIso": "2026-06-24T22:39:00.000Z",
      "timeLabel": "Wed 11:39 pm",
      "heightM": 1.8654021817831157
    },
    {
      "type": "high",
      "timeIso": "2026-06-25T04:21:00.000Z",
      "timeLabel": "Thu 5:21 am",
      "heightM": 3.641582310406899
    },
    {
      "type": "low",
      "timeIso": "2026-06-25T11:44:00.000Z",
      "timeLabel": "Thu 12:44 pm",
      "heightM": 1.7492558913376826
    },
    {
      "type": "high",
      "timeIso": "2026-06-25T17:01:00.000Z",
      "timeLabel": "Thu 6:01 pm",
      "heightM": 3.497901005564708
    },
    {
      "type": "low",
      "timeIso": "2026-06-26T00:09:00.000Z",
      "timeLabel": "Fri 1:09 am",
      "heightM": 1.783162748389487
    },
    {
      "type": "high",
      "timeIso": "2026-06-26T05:30:00.000Z",
      "timeLabel": "Fri 6:30 am",
      "heightM": 3.693223766376322
    }
  ]
}
