{
  "fetchedAt": "2026-05-30T21:22:47.471Z",
  "station": "Tywyn",
  "upcoming": [
    {
      "type": "low",
      "timeIso": "2026-05-31T02:42:00.000Z",
      "timeLabel": "Sun 3:42 am",
      "heightM": 1.1902528764826048
    },
    {
      "type": "high",
      "timeIso": "2026-05-31T08:00:00.000Z",
      "timeLabel": "Sun 9:00 am",
      "heightM": 4.283150810871225
    },
    {
      "type": "low",
      "timeIso": "2026-05-31T15:02:00.000Z",
      "timeLabel": "Sun 4:02 pm",
      "heightM": 1.2596009221269198
    },
    {
      "type": "high",
      "timeIso": "2026-05-31T20:15:00.000Z",
      "timeLabel": "Sun 9:15 pm",
      "heightM": 4.230048237522292
    },
    {
      "type": "low",
      "timeIso": "2026-06-01T03:16:00.000Z",
      "timeLabel": "Mon 4:16 am",
      "heightM": 1.1806322824411917
    },
    {
      "type": "high",
      "timeIso": "2026-06-01T08:35:00.000Z",
      "timeLabel": "Mon 9:35 am",
      "heightM": 4.273039250453028
    }
  ]
}
